LICENSE
MANIFEST.in
README.md
setup.cfg
setup.py
simple_social_suture/__init__.py
simple_social_suture/api.py
simple_social_suture.egg-info/PKG-INFO
simple_social_suture.egg-info/SOURCES.txt
simple_social_suture.egg-info/dependency_links.txt
simple_social_suture.egg-info/top_level.txt