Metadata-Version: 1.1
Name: simple-social-suture
Version: 0.6
Summary: Retrieve and combine content from various social networks into a unified format
Home-page: https://github.com/ninapavlich/simple-social-suture
Author: Nina Pavlich
Author-email: nina@ninalp.com
License: MIT
Keywords: libraries,web development,social network,python,twitter,instagram
Platform: UNKNOWN
Classifier: Development Status :: 4 - Beta
Classifier: Environment :: Web Environment
Classifier: Intended Audience :: Developers
Classifier: License :: OSI Approved :: MIT License
Classifier: Natural Language :: English
Classifier: Operating System :: OS Independent
Classifier: Programming Language :: Python
